garpy/__init__.py
garpy/activity.py
garpy/cli.py
garpy/download.py
garpy/resources/default_config.yaml
garpy/settings.py
garpy/wellness.py
garpy-0.4.0.dist-info/LICENSE
garpy-0.4.0.dist-info/METADATA
garpy-0.4.0.dist-info/WHEEL
garpy-0.4.0.dist-info/entry_points.txt
garpy-0.4.0.dist-info/RECORD
