Metadata-Version: 2.1
Name: garpy
Version: 0.4.0
Summary: Python client for downloading activities from Garmin Connect
Home-page: https://github.com/felipeam86/garpy
License: MIT
Author: Felipe Aguirre Martinez
Author-email: felipeam86@gmail.com
Requires-Python: >=3.7.9,<4.0.0
Classifier: License :: OSI Approved :: MIT License
Classifier: Programming Language :: Python :: 3
Classifier: Programming Language :: Python :: 3.8
Classifier: Programming Language :: Python :: 3.9
Classifier: Programming Language :: Python :: 3.10
Classifier: Programming Language :: Python :: 3.11
Requires-Dist: PyYAML (>=5.1,<7.0)
Requires-Dist: attrs (>=21.4.0,<22.0.0)
Requires-Dist: click (>=7,<9)
Requires-Dist: cloudscraper (>=1.2.58,<2.0.0)
Requires-Dist: garpyclient (>=0.1.1,<0.2.0)
Requires-Dist: pendulum (>=2.0,<3.0)
Requires-Dist: requests (>=2.22,<3.0)
Requires-Dist: tqdm (>=4.36,<5.0)
